{
  "logs": [
    {
      "id": 3,
      "message": "server is up and running in 1121",
      "attention": false,
      "tech": "John Doe",
      "date": "2021-05-14T18:17:08.283Z"
    },
    {
      "message": "Connection to the internet is fixed ",
      "attention": false,
      "tech": "Sam Smith",
      "date": "2021-05-14T17:54:26.340Z",
      "id": 4
    }
  ],
  "techs": [
    {
      "id": 2,
      "firstName": "Sam",
      "lastName": "Smith"
    },
    {
      "id": 3,
      "firstName": "Sara",
      "lastName": "Wilson"
    },
    {
      "firstName": "Mark",
      "lastName": "Zuckerberg",
      "id": 4
    },
    {
      "firstName": "Jim",
      "lastName": "Carrey",
      "id": 5
    }
  ]
}